{
  "project": "sharewithfriends",
  "platform": "Cloudflare Pages",
  "setup_instructions": {
    "step_1": "Go to Cloudflare Dashboard → Workers & Pages → Pages.",
    "step_2": "Click Create → Pages project (⚠️ NOT Worker).",
    "step_3": "Connect GitHub repo: BlueberryCloud/ShareWithFriends (branch: master or v2).",
    "step_4": {
      "build_command": "echo \"no build\" && exit 0",
      "output_directory": "/",
      "root_directory": "(leave blank)"
    },
    "step_5": "Click Save and Deploy. Wait for deployment to finish.",
    "step_6": "Verify live site at https://sharewithfriends.pages.dev",
    "reset_note": "If deployment fails with 'cp: not found' or similar, go to Settings → Build & Deploy and reapply step_4."
  },
  "mechanism_explained": {
    "github_integration": "When you push a commit to the repo, Cloudflare Pages automatically fetches the repo contents.",
    "build_stage": "Normally Pages runs a build step (npm, Hugo, etc). With our custom command, we skip that by running a no-op.",
    "deployment_stage": "After skipping the build, Pages directly publishes the files from the repo root ('/').",
    "domain_mapping": "Every Pages project gets a <project>.pages.dev domain. Our project name 'sharewithfriends' maps to 'sharewithfriends.pages.dev'.",
    "why_custom_build": "Without the no-op command, Cloudflare auto-generates a build script that fails because our repo has no Node, Hugo, or dist/ output. The custom build tells Pages to just copy static files as-is."
  },
  "ascii_pipeline": [
    "GitHub Repo (BlueberryCloud/ShareWithFriends)",
    "        │ push",
    "        ▼",
    "Cloudflare Pages Project 'sharewithfriends'",
    "        │ build command: echo \"no build\" && exit 0",
    "        │ output dir: /",
    "        ▼",
    "Deployment → publish static files as-is",
    "        ▼",
    "Live Domain: https://sharewithfriends.pages.dev"
  ]
}
